setup.py
Pucks.egg-info/PKG-INFO
Pucks.egg-info/SOURCES.txt
Pucks.egg-info/dependency_links.txt
Pucks.egg-info/not-zip-safe
Pucks.egg-info/requires.txt
Pucks.egg-info/top_level.txt
puck/__init__.py
puck/app.py
puck/constants.py
puck/cookies.py
puck/data_structures.py
puck/example.py
puck/exceptions.py
puck/form.py
puck/globals.py
puck/helper.py
puck/local.py
puck/param_parser.py
puck/request.py
puck/response.py
puck/routing.py
puck/routing_test.py
puck/server.py
puck/session.py
puck/utils.py