Metadata-Version: 1.0
Name: Pucks
Version: 0.1.2
Summary: A web micro-frame, quickly developing restful api.
Home-page: https://github.com/EricQAQ/Puck
Author: Eric Zhang
Author-email: eric.pucker@gmail.com
License: MIT
Platform: any
